comfygit_cli/__init__.py
comfygit_cli/__main__.py
comfygit_cli/cli.py
comfygit_cli/cli_utils.py
comfygit_cli/completers.py
comfygit_cli/completion_commands.py
comfygit_cli/env_commands.py
comfygit_cli/global_commands.py
comfygit_cli/resolution_strategies.py
comfygit_cli/formatters/__init__.py
comfygit_cli/formatters/error_formatter.py
comfygit_cli/interactive/__init__.py
comfygit_cli/logging/compressed_handler.py
comfygit_cli/logging/environment_logger.py
comfygit_cli/logging/log_compressor.py
comfygit_cli/logging/logging_config.py
comfygit_cli/strategies/__init__.py
comfygit_cli/strategies/conflict_resolver.py
comfygit_cli/strategies/interactive.py
comfygit_cli/strategies/rollback.py
comfygit_cli/utils/__init__.py
comfygit_cli/utils/civitai_errors.py
comfygit_cli/utils/orchestrator.py
comfygit_cli/utils/pagination.py
comfygit_cli/utils/progress.py
comfygit-0.3.12.dist-info/METADATA
comfygit-0.3.12.dist-info/WHEEL
comfygit-0.3.12.dist-info/entry_points.txt
comfygit-0.3.12.dist-info/licenses/LICENSE.txt
comfygit-0.3.12.dist-info/RECORD
