Metadata-Version: 2.4
Name: comfygit
Version: 0.3.12
Summary: ComfyGit - Git-based environment management for ComfyUI
License-File: LICENSE.txt
Requires-Python: >=3.10
Requires-Dist: argcomplete>=3.5.0
Requires-Dist: comfygit-core==0.3.12
